fastapi_keycloack/__init__.py
fastapi_keycloack/fastapi_keycloack.py
fastapi_keycloack-0.2.1.dist-info/LICENSE
fastapi_keycloack-0.2.1.dist-info/WHEEL
fastapi_keycloack-0.2.1.dist-info/METADATA
fastapi_keycloack-0.2.1.dist-info/RECORD
