Metadata-Version: 2.1
Name: fastapi-keycloack
Version: 0.2.1
Summary: 
Home-page: https://github.com/elbernv/fastapi-keycloack
License: MIT
Author: Elber Nava
Author-email: elbernava11@gmail.com
Requires-Python: >=3.8,<4.0
Classifier: License :: OSI Approved :: MIT License
Classifier: Programming Language :: Python :: 3
Classifier: Programming Language :: Python :: 3.10
Classifier: Programming Language :: Python :: 3.8
Classifier: Programming Language :: Python :: 3.9
Requires-Dist: python-jose (>=3.3.0,<4.0.0)
Project-URL: Repository, https://github.com/elbernv/fastapi-keycloack
